search_comparator/__init__.py
search_comparator/comparator.py
search_comparator/query.py
search_comparator/rbo.py
search_comparator/results.py
search_comparator-0.1.0.dist-info/METADATA
search_comparator-0.1.0.dist-info/WHEEL
search_comparator-0.1.0.dist-info/top_level.txt
search_comparator-0.1.0.dist-info/RECORD
