Metadata-Version: 2.1
Name: search-comparator
Version: 0.1.0
Summary: A search comparator
Home-page: UNKNOWN
Author: Relevance AI
Author-email: dev@vctr.ai
License: UNKNOWN
Platform: UNKNOWN
